ModelMagicAPI/__init__.py
ModelMagicAPI/admin.py
ModelMagicAPI/apps.py
ModelMagicAPI/autoapi.py
ModelMagicAPI/exceptions.py
ModelMagicAPI/models.py
ModelMagicAPI/signals.py
ModelMagicAPI/tests.py
ModelMagicAPI/utils.py
ModelMagicAPI/views.py
ModelMagicAPI/migrations/0001_initial.py
ModelMagicAPI/migrations/__init__.py
crudify/__init__.py
crudify/asgi.py
crudify/settings.py
crudify/urls.py
crudify/wsgi.py
crudify-0.1.0.dist-info/METADATA
crudify-0.1.0.dist-info/WHEEL
crudify-0.1.0.dist-info/top_level.txt
crudify-0.1.0.dist-info/RECORD
